mango_mdschema/__init__.py
mango_mdschema/constants.py
mango_mdschema/exceptions.py
mango_mdschema/fields.py
mango_mdschema/helpers.py
mango_mdschema/schema.py
mango_mdschema-1.0.3.dist-info/LICENSE
mango_mdschema-1.0.3.dist-info/METADATA
mango_mdschema-1.0.3.dist-info/WHEEL
mango_mdschema-1.0.3.dist-info/top_level.txt
mango_mdschema-1.0.3.dist-info/RECORD
