Metadata-Version: 2.2
Name: mango-mdschema
Version: 1.0.3
Summary: ManGO metadata schemas on iRODS
Author-email: Mariana Montes <mariana.montes@kuleuven.be>, Ronny Moreas <ronny.moreas@kuleuven.be>
License: MIT License
Project-URL: repository, https://github.com/kuleuven/mango-mdschema
Requires-Python: >=3.8
License-File: LICENSE
Requires-Dist: python-irodsclient>=1.1.1
Requires-Dist: validators>=0.22.0
Provides-Extra: dev
